{
  "meta": {
    "source": "live"
  },
  "results": {
    "etag": "g7q_yw1rjOWJjDqAlWssaSZELD4",
    "items": [
      {
        "etag": "KDokw-xZzRACHluumWXOZo-D2tY",
        "id": {
          "kind": "youtube#video",
          "videoId": "BRocA7husPU"
        },
        "kind": "youtube#searchResult",
        "snippet": {
          "channelId": "UCZm2kvByDm6st8b_x7Dsf7w",
          "channelTitle": "Climbo - Start Your AI Business",
          "description": "Start Your AI Business: https://climbo.com Free Community: https://skool.climbo.com.",
          "liveBroadcastContent": "none",
          "publishTime": "2026-03-20T11:15:38Z",
          "publishedAt": "2026-03-20T11:15:38Z",
          "thumbnails": {
            "default": {
              "height": 90,
              "url": "https://i.ytimg.com/vi/BRocA7husPU/default.jpg",
              "width": 120
            },
            "high": {
              "height": 360,
              "url": "https://i.ytimg.com/vi/BRocA7husPU/hqdefault.jpg",
              "width": 480
            },
            "medium": {
              "height": 180,
              "url": "https://i.ytimg.com/vi/BRocA7husPU/mqdefault.jpg",
              "width": 320
            }
          },
          "title": "Start a $3k/mo Reputation Management Business (No GHL Complex Setup)"
        }
      },
      {
        "etag": "BGio8N57bl4WLLaa5DKoYi6Z8Og",
        "id": {
          "kind": "youtube#video",
          "videoId": "sIGOLZ1kFAQ"
        },
        "kind": "youtube#searchResult",
        "snippet": {
          "channelId": "UCZm2kvByDm6st8b_x7Dsf7w",
          "channelTitle": "Climbo - Start Your AI Business",
          "description": "Start Your AI Business: https://climbo.com Free Community: https://skool.climbo.com.",
          "liveBroadcastContent": "none",
          "publishTime": "2026-05-18T09:34:26Z",
          "publishedAt": "2026-05-18T09:34:26Z",
          "thumbnails": {
            "default": {
              "height": 90,
              "url": "https://i.ytimg.com/vi/sIGOLZ1kFAQ/default.jpg",
              "width": 120
            },
            "high": {
              "height": 360,
              "url": "https://i.ytimg.com/vi/sIGOLZ1kFAQ/hqdefault.jpg",
              "width": 480
            },
            "medium": {
              "height": 180,
              "url": "https://i.ytimg.com/vi/sIGOLZ1kFAQ/mqdefault.jpg",
              "width": 320
            }
          },
          "title": "Climbo in 1 minute"
        }
      },
      {
        "etag": "8lS2u3AxblhoDoQca5PzlR05qQ4",
        "id": {
          "kind": "youtube#video",
          "videoId": "PQiNrTKVLOU"
        },
        "kind": "youtube#searchResult",
        "snippet": {
          "channelId": "UCZm2kvByDm6st8b_x7Dsf7w",
          "channelTitle": "Climbo - Start Your AI Business",
          "description": "Start Your AI Business: https://climbo.com Free Community: https://skool.climbo.com.",
          "liveBroadcastContent": "none",
          "publishTime": "2026-01-16T16:27:55Z",
          "publishedAt": "2026-01-16T16:27:55Z",
          "thumbnails": {
            "default": {
              "height": 90,
              "url": "https://i.ytimg.com/vi/PQiNrTKVLOU/default.jpg",
              "width": 120
            },
            "high": {
              "height": 360,
              "url": "https://i.ytimg.com/vi/PQiNrTKVLOU/hqdefault.jpg",
              "width": 480
            },
            "medium": {
              "height": 180,
              "url": "https://i.ytimg.com/vi/PQiNrTKVLOU/mqdefault.jpg",
              "width": 320
            }
          },
          "title": "Climbo Restart: Features Drop, New Community, New Website \u0026amp; Pricing, Mobile Apps"
        }
      },
      {
        "etag": "2wEAXua_OGcTjOJ4v5F0gulcpho",
        "id": {
          "kind": "youtube#video",
          "videoId": "esTnEB5CyzA"
        },
        "kind": "youtube#searchResult",
        "snippet": {
          "channelId": "UCZm2kvByDm6st8b_x7Dsf7w",
          "channelTitle": "Climbo - Start Your AI Business",
          "description": "Start Your AI Business: https://climbo.com Free Community: https://skool.climbo.com.",
          "liveBroadcastContent": "none",
          "publishTime": "2026-05-08T12:53:50Z",
          "publishedAt": "2026-05-08T12:53:50Z",
          "thumbnails": {
            "default": {
              "height": 90,
              "url": "https://i.ytimg.com/vi/esTnEB5CyzA/default.jpg",
              "width": 120
            },
            "high": {
              "height": 360,
              "url": "https://i.ytimg.com/vi/esTnEB5CyzA/hqdefault.jpg",
              "width": 480
            },
            "medium": {
              "height": 180,
              "url": "https://i.ytimg.com/vi/esTnEB5CyzA/mqdefault.jpg",
              "width": 320
            }
          },
          "title": "Live A.M.A. (07/04052026) - AI Ranking is Here!"
        }
      },
      {
        "etag": "K_PnhcOJuEIZG2UtzFxZjfOgMmo",
        "id": {
          "kind": "youtube#video",
          "videoId": "FXjbN3T1BU8"
        },
        "kind": "youtube#searchResult",
        "snippet": {
          "channelId": "UCZm2kvByDm6st8b_x7Dsf7w",
          "channelTitle": "Climbo - Start Your AI Business",
          "description": "Start Your AI Business: https://climbo.com Free Community: https://skool.climbo.com.",
          "liveBroadcastContent": "none",
          "publishTime": "2026-02-12T21:33:03Z",
          "publishedAt": "2026-02-12T21:33:03Z",
          "thumbnails": {
            "default": {
              "height": 90,
              "url": "https://i.ytimg.com/vi/FXjbN3T1BU8/default.jpg",
              "width": 120
            },
            "high": {
              "height": 360,
              "url": "https://i.ytimg.com/vi/FXjbN3T1BU8/hqdefault.jpg",
              "width": 480
            },
            "medium": {
              "height": 180,
              "url": "https://i.ytimg.com/vi/FXjbN3T1BU8/mqdefault.jpg",
              "width": 320
            }
          },
          "title": "Live A.M.A. (12/02/2026) - Automated Website For Clients \u0026amp; Instant Google Reviews"
        }
      },
      {
        "etag": "aAXJ5hunle-OgyhTgm67fh68QXE",
        "id": {
          "kind": "youtube#video",
          "videoId": "LIn64wsy8wA"
        },
        "kind": "youtube#searchResult",
        "snippet": {
          "channelId": "UCZm2kvByDm6st8b_x7Dsf7w",
          "channelTitle": "Climbo - Start Your AI Business",
          "description": "Start Your AI Business: https://climbo.com Free Community: https://skool.climbo.com.",
          "liveBroadcastContent": "none",
          "publishTime": "2026-04-17T07:44:45Z",
          "publishedAt": "2026-04-17T07:44:45Z",
          "thumbnails": {
            "default": {
              "height": 90,
              "url": "https://i.ytimg.com/vi/LIn64wsy8wA/default.jpg",
              "width": 120
            },
            "high": {
              "height": 360,
              "url": "https://i.ytimg.com/vi/LIn64wsy8wA/hqdefault.jpg",
              "width": 480
            },
            "medium": {
              "height": 180,
              "url": "https://i.ytimg.com/vi/LIn64wsy8wA/mqdefault.jpg",
              "width": 320
            }
          },
          "title": "Live A.M.A. (17/04/2026) - GEO Agent is Live!"
        }
      },
      {
        "etag": "7IqTTnf7V8D7aQfmwbYK8i8xAQ8",
        "id": {
          "kind": "youtube#video",
          "videoId": "Y-JnPapla-8"
        },
        "kind": "youtube#searchResult",
        "snippet": {
          "channelId": "UCZm2kvByDm6st8b_x7Dsf7w",
          "channelTitle": "Climbo - Start Your AI Business",
          "description": "Start Your AI Business: https://climbo.com Free Community: https://skool.climbo.com.",
          "liveBroadcastContent": "none",
          "publishTime": "2026-01-23T11:01:59Z",
          "publishedAt": "2026-01-23T11:01:59Z",
          "thumbnails": {
            "default": {
              "height": 90,
              "url": "https://i.ytimg.com/vi/Y-JnPapla-8/default.jpg",
              "width": 120
            },
            "high": {
              "height": 360,
              "url": "https://i.ytimg.com/vi/Y-JnPapla-8/hqdefault.jpg",
              "width": 480
            },
            "medium": {
              "height": 180,
              "url": "https://i.ytimg.com/vi/Y-JnPapla-8/mqdefault.jpg",
              "width": 320
            }
          },
          "title": "Live A.M.A. (22/01/2026) - Monthly Sales Trainings, Coupon Codes \u0026amp; Package Pricing"
        }
      },
      {
        "etag": "_xB2fqsU3V6obnDDnAO7VWnoJU4",
        "id": {
          "kind": "youtube#video",
          "videoId": "hg7302kRED4"
        },
        "kind": "youtube#searchResult",
        "snippet": {
          "channelId": "UCZm2kvByDm6st8b_x7Dsf7w",
          "channelTitle": "Climbo - Start Your AI Business",
          "description": "",
          "liveBroadcastContent": "none",
          "publishTime": "2026-07-02T15:57:56Z",
          "publishedAt": "2026-07-02T15:57:56Z",
          "thumbnails": {
            "default": {
              "height": 90,
              "url": "https://i.ytimg.com/vi/hg7302kRED4/default.jpg",
              "width": 120
            },
            "high": {
              "height": 360,
              "url": "https://i.ytimg.com/vi/hg7302kRED4/hqdefault.jpg",
              "width": 480
            },
            "medium": {
              "height": 180,
              "url": "https://i.ytimg.com/vi/hg7302kRED4/mqdefault.jpg",
              "width": 320
            }
          },
          "title": "Apply at climbo.com"
        }
      },
      {
        "etag": "OUKopuw8Bh_5cxkfSOJXOzqWKrE",
        "id": {
          "kind": "youtube#video",
          "videoId": "VibWfDfMwVA"
        },
        "kind": "youtube#searchResult",
        "snippet": {
          "channelId": "UCZm2kvByDm6st8b_x7Dsf7w",
          "channelTitle": "Climbo - Start Your AI Business",
          "description": "Start Your AI Business: https://climbo.com Free Community: https://skool.climbo.com.",
          "liveBroadcastContent": "none",
          "publishTime": "2026-01-30T14:57:55Z",
          "publishedAt": "2026-01-30T14:57:55Z",
          "thumbnails": {
            "default": {
              "height": 90,
              "url": "https://i.ytimg.com/vi/VibWfDfMwVA/default.jpg",
              "width": 120
            },
            "high": {
              "height": 360,
              "url": "https://i.ytimg.com/vi/VibWfDfMwVA/hqdefault.jpg",
              "width": 480
            },
            "medium": {
              "height": 180,
              "url": "https://i.ytimg.com/vi/VibWfDfMwVA/mqdefault.jpg",
              "width": 320
            }
          },
          "title": "Live A.M.A. (29/01/2026) - Custom AI Prompt, Bulk Review Replies, Video on Review Link, \u0026amp; More!"
        }
      },
      {
        "etag": "NuMOeoy5fwgn47RlokppkANTkwA",
        "id": {
          "kind": "youtube#video",
          "videoId": "rJhFyiE_Yvk"
        },
        "kind": "youtube#searchResult",
        "snippet": {
          "channelId": "UCZm2kvByDm6st8b_x7Dsf7w",
          "channelTitle": "Climbo - Start Your AI Business",
          "description": "Start Your AI Business: https://climbo.com Free Community: https://skool.climbo.com.",
          "liveBroadcastContent": "none",
          "publishTime": "2026-05-21T15:49:33Z",
          "publishedAt": "2026-05-21T15:49:33Z",
          "thumbnails": {
            "default": {
              "height": 90,
              "url": "https://i.ytimg.com/vi/rJhFyiE_Yvk/default.jpg",
              "width": 120
            },
            "high": {
              "height": 360,
              "url": "https://i.ytimg.com/vi/rJhFyiE_Yvk/hqdefault.jpg",
              "width": 480
            },
            "medium": {
              "height": 180,
              "url": "https://i.ytimg.com/vi/rJhFyiE_Yvk/mqdefault.jpg",
              "width": 320
            }
          },
          "title": "Live A.M.A. (21/05/2026) - Your Branded AI Is Here!"
        }
      },
      {
        "etag": "NVqyV0LYQhOTzDjC9sj3zIHL8EM",
        "id": {
          "kind": "youtube#video",
          "videoId": "6Mj7hZUtfAA"
        },
        "kind": "youtube#searchResult",
        "snippet": {
          "channelId": "UCZm2kvByDm6st8b_x7Dsf7w",
          "channelTitle": "Climbo - Start Your AI Business",
          "description": "Start Your AI Business: https://climbo.com Free Community: https://skool.climbo.com.",
          "liveBroadcastContent": "none",
          "publishTime": "2026-04-10T12:59:20Z",
          "publishedAt": "2026-04-10T12:59:20Z",
          "thumbnails": {
            "default": {
              "height": 90,
              "url": "https://i.ytimg.com/vi/6Mj7hZUtfAA/default.jpg",
              "width": 120
            },
            "high": {
              "height": 360,
              "url": "https://i.ytimg.com/vi/6Mj7hZUtfAA/hqdefault.jpg",
              "width": 480
            },
            "medium": {
              "height": 180,
              "url": "https://i.ytimg.com/vi/6Mj7hZUtfAA/mqdefault.jpg",
              "width": 320
            }
          },
          "title": "Live A.M.A. (09/04/2026) - GEO Agent is Coming! #2"
        }
      },
      {
        "etag": "oUGmqWLXtFr_sRcQmYCNC_QtbP0",
        "id": {
          "kind": "youtube#video",
          "videoId": "pbGfIjJEwFE"
        },
        "kind": "youtube#searchResult",
        "snippet": {
          "channelId": "UCZm2kvByDm6st8b_x7Dsf7w",
          "channelTitle": "Climbo - Start Your AI Business",
          "description": "Start Your AI Business: https://climbo.com Free Community: https://skool.climbo.com.",
          "liveBroadcastContent": "none",
          "publishTime": "2026-02-19T21:17:09Z",
          "publishedAt": "2026-02-19T21:17:09Z",
          "thumbnails": {
            "default": {
              "height": 90,
              "url": "https://i.ytimg.com/vi/pbGfIjJEwFE/default.jpg",
              "width": 120
            },
            "high": {
              "height": 360,
              "url": "https://i.ytimg.com/vi/pbGfIjJEwFE/hqdefault.jpg",
              "width": 480
            },
            "medium": {
              "height": 180,
              "url": "https://i.ytimg.com/vi/pbGfIjJEwFE/mqdefault.jpg",
              "width": 320
            }
          },
          "title": "Live A.M.A. (19/02/2026) - Video Reviews Widgets, AI Chatbot, Webhook Builder \u0026amp; More!"
        }
      },
      {
        "etag": "aIrfq4OEeLXzKigLsy0fNaCcCzA",
        "id": {
          "kind": "youtube#video",
          "videoId": "WUPOkx48fGY"
        },
        "kind": "youtube#searchResult",
        "snippet": {
          "channelId": "UCZm2kvByDm6st8b_x7Dsf7w",
          "channelTitle": "Climbo - Start Your AI Business",
          "description": "Start Your AI Business: https://climbo.com Free Community: https://skool.climbo.com.",
          "liveBroadcastContent": "none",
          "publishTime": "2026-04-24T08:05:39Z",
          "publishedAt": "2026-04-24T08:05:39Z",
          "thumbnails": {
            "default": {
              "height": 90,
              "url": "https://i.ytimg.com/vi/WUPOkx48fGY/default.jpg",
              "width": 120
            },
            "high": {
              "height": 360,
              "url": "https://i.ytimg.com/vi/WUPOkx48fGY/hqdefault.jpg",
              "width": 480
            },
            "medium": {
              "height": 180,
              "url": "https://i.ytimg.com/vi/WUPOkx48fGY/mqdefault.jpg",
              "width": 320
            }
          },
          "title": "Live A.M.A. (23/04/2026) - Employees Tracking \u0026amp; Leaderboard + New UI Clients Mode"
        }
      },
      {
        "etag": "7KS1d-nbxcVQmouz9XbT-uYOpSs",
        "id": {
          "kind": "youtube#video",
          "videoId": "FtEM-FRfOgo"
        },
        "kind": "youtube#searchResult",
        "snippet": {
          "channelId": "UCZm2kvByDm6st8b_x7Dsf7w",
          "channelTitle": "Climbo - Start Your AI Business",
          "description": "Start Your AI Business: https://climbo.com Free Community: https://skool.climbo.com.",
          "liveBroadcastContent": "none",
          "publishTime": "2026-02-05T21:43:35Z",
          "publishedAt": "2026-02-05T21:43:35Z",
          "thumbnails": {
            "default": {
              "height": 90,
              "url": "https://i.ytimg.com/vi/FtEM-FRfOgo/default.jpg",
              "width": 120
            },
            "high": {
              "height": 360,
              "url": "https://i.ytimg.com/vi/FtEM-FRfOgo/hqdefault.jpg",
              "width": 480
            },
            "medium": {
              "height": 180,
              "url": "https://i.ytimg.com/vi/FtEM-FRfOgo/mqdefault.jpg",
              "width": 320
            }
          },
          "title": "Live A.M.A. (05/02/2026) - Agency Email Templates, Pre-Built Website For Clients, GEO Agent Coming!"
        }
      },
      {
        "etag": "EaJj-rRBSASLSRo8pa4UKvRFyVo",
        "id": {
          "kind": "youtube#video",
          "videoId": "Cbw27lPDN-c"
        },
        "kind": "youtube#searchResult",
        "snippet": {
          "channelId": "UCZm2kvByDm6st8b_x7Dsf7w",
          "channelTitle": "Climbo - Start Your AI Business",
          "description": "Start Your AI Business: https://climbo.com Free Community: https://skool.climbo.com.",
          "liveBroadcastContent": "none",
          "publishTime": "2026-03-27T11:25:55Z",
          "publishedAt": "2026-03-27T11:25:55Z",
          "thumbnails": {
            "default": {
              "height": 90,
              "url": "https://i.ytimg.com/vi/Cbw27lPDN-c/default.jpg",
              "width": 120
            },
            "high": {
              "height": 360,
              "url": "https://i.ytimg.com/vi/Cbw27lPDN-c/hqdefault.jpg",
              "width": 480
            },
            "medium": {
              "height": 180,
              "url": "https://i.ytimg.com/vi/Cbw27lPDN-c/mqdefault.jpg",
              "width": 320
            }
          },
          "title": "Live A.M.A. (26/03/2026) - Email Reminders, Review Link Auto Translation, Printable Reports, \u0026amp; More!"
        }
      },
      {
        "etag": "UxZdlHBMAblRgfyFFqFT1jBJb3s",
        "id": {
          "kind": "youtube#video",
          "videoId": "0Jek3W4-9pk"
        },
        "kind": "youtube#searchResult",
        "snippet": {
          "channelId": "UCZm2kvByDm6st8b_x7Dsf7w",
          "channelTitle": "Climbo - Start Your AI Business",
          "description": "Start Your AI Business: https://climbo.com Free Community: https://skool.climbo.com.",
          "liveBroadcastContent": "none",
          "publishTime": "2026-05-01T09:18:15Z",
          "publishedAt": "2026-05-01T09:18:15Z",
          "thumbnails": {
            "default": {
              "height": 90,
              "url": "https://i.ytimg.com/vi/0Jek3W4-9pk/default.jpg",
              "width": 120
            },
            "high": {
              "height": 360,
              "url": "https://i.ytimg.com/vi/0Jek3W4-9pk/hqdefault.jpg",
              "width": 480
            },
            "medium": {
              "height": 180,
              "url": "https://i.ytimg.com/vi/0Jek3W4-9pk/mqdefault.jpg",
              "width": 320
            }
          },
          "title": "Live A.M.A. (23/04/2026) - Embed GEO Agent + Fixes \u0026amp; Improvements!"
        }
      },
      {
        "etag": "dA8dXg3pg9HPkX8-vbeTdiN3r-Y",
        "id": {
          "kind": "youtube#video",
          "videoId": "i4D5yXclzEY"
        },
        "kind": "youtube#searchResult",
        "snippet": {
          "channelId": "UCZm2kvByDm6st8b_x7Dsf7w",
          "channelTitle": "Climbo - Start Your AI Business",
          "description": "Start Your AI Business: https://climbo.com Free Community: https://skool.climbo.com.",
          "liveBroadcastContent": "none",
          "publishTime": "2026-02-26T19:35:55Z",
          "publishedAt": "2026-02-26T19:35:55Z",
          "thumbnails": {
            "default": {
              "height": 90,
              "url": "https://i.ytimg.com/vi/i4D5yXclzEY/default.jpg",
              "width": 120
            },
            "high": {
              "height": 360,
              "url": "https://i.ytimg.com/vi/i4D5yXclzEY/hqdefault.jpg",
              "width": 480
            },
            "medium": {
              "height": 180,
              "url": "https://i.ytimg.com/vi/i4D5yXclzEY/mqdefault.jpg",
              "width": 320
            }
          },
          "title": "Live A.M.A. (26/02/2026) - AI Review Suggestion is Here!"
        }
      },
      {
        "etag": "wMfxfmkpTwqO-5ihyuCvl5ZansU",
        "id": {
          "kind": "youtube#video",
          "videoId": "Q2RkdIdJBoY"
        },
        "kind": "youtube#searchResult",
        "snippet": {
          "channelId": "UCZm2kvByDm6st8b_x7Dsf7w",
          "channelTitle": "Climbo - Start Your AI Business",
          "description": "Start Your AI Business: https://climbo.com Free Community: https://skool.climbo.com.",
          "liveBroadcastContent": "none",
          "publishTime": "2026-04-01T09:50:57Z",
          "publishedAt": "2026-04-01T09:50:57Z",
          "thumbnails": {
            "default": {
              "height": 90,
              "url": "https://i.ytimg.com/vi/Q2RkdIdJBoY/default.jpg",
              "width": 120
            },
            "high": {
              "height": 360,
              "url": "https://i.ytimg.com/vi/Q2RkdIdJBoY/hqdefault.jpg",
              "width": 480
            },
            "medium": {
              "height": 180,
              "url": "https://i.ytimg.com/vi/Q2RkdIdJBoY/mqdefault.jpg",
              "width": 320
            }
          },
          "title": "Live A.M.A. (31/03/2026) - Your Branded iOS \u0026amp; Android Mobile App!"
        }
      },
      {
        "etag": "DRewZ2yJ6SM8IrBAn9gxvFPPGVA",
        "id": {
          "kind": "youtube#video",
          "videoId": "w3upDdv8hlY"
        },
        "kind": "youtube#searchResult",
        "snippet": {
          "channelId": "UCZm2kvByDm6st8b_x7Dsf7w",
          "channelTitle": "Climbo - Start Your AI Business",
          "description": "Start Your AI Business: https://climbo.com Free Community: https://skool.climbo.com.",
          "liveBroadcastContent": "none",
          "publishTime": "2026-03-20T10:28:14Z",
          "publishedAt": "2026-03-20T10:28:14Z",
          "thumbnails": {
            "default": {
              "height": 90,
              "url": "https://i.ytimg.com/vi/w3upDdv8hlY/default.jpg",
              "width": 120
            },
            "high": {
              "height": 360,
              "url": "https://i.ytimg.com/vi/w3upDdv8hlY/hqdefault.jpg",
              "width": 480
            },
            "medium": {
              "height": 180,
              "url": "https://i.ytimg.com/vi/w3upDdv8hlY/mqdefault.jpg",
              "width": 320
            }
          },
          "title": "Live A.M.A. (19/03/2026) - Clients Filter, Booking Links, Demo Per Category \u0026amp; More!"
        }
      },
      {
        "etag": "XHiSpakuIXRYxMqbdwfRrM4vyxQ",
        "id": {
          "kind": "youtube#video",
          "videoId": "yFsRXQ4E9Wc"
        },
        "kind": "youtube#searchResult",
        "snippet": {
          "channelId": "UCZm2kvByDm6st8b_x7Dsf7w",
          "channelTitle": "Climbo - Start Your AI Business",
          "description": "Start Your AI Business: https://climbo.com Free Community: https://skool.climbo.com.",
          "liveBroadcastContent": "none",
          "publishTime": "2026-05-15T08:16:51Z",
          "publishedAt": "2026-05-15T08:16:51Z",
          "thumbnails": {
            "default": {
              "height": 90,
              "url": "https://i.ytimg.com/vi/yFsRXQ4E9Wc/default.jpg",
              "width": 120
            },
            "high": {
              "height": 360,
              "url": "https://i.ytimg.com/vi/yFsRXQ4E9Wc/hqdefault.jpg",
              "width": 480
            },
            "medium": {
              "height": 180,
              "url": "https://i.ytimg.com/vi/yFsRXQ4E9Wc/mqdefault.jpg",
              "width": 320
            }
          },
          "title": "Live A.M.A. (14/05/2026) - Google Sheets Integration \u0026amp; Complaint Review Link!"
        }
      },
      {
        "etag": "o5tBmozTnhKdxeOTKHA7HKk5I3U",
        "id": {
          "kind": "youtube#video",
          "videoId": "ctiVjKi2LrU"
        },
        "kind": "youtube#searchResult",
        "snippet": {
          "channelId": "UCZm2kvByDm6st8b_x7Dsf7w",
          "channelTitle": "Climbo - Start Your AI Business",
          "description": "Start Your AI Business: https://climbo.com Free Community: https://skool.climbo.com.",
          "liveBroadcastContent": "none",
          "publishTime": "2026-04-02T18:52:05Z",
          "publishedAt": "2026-04-02T18:52:05Z",
          "thumbnails": {
            "default": {
              "height": 90,
              "url": "https://i.ytimg.com/vi/ctiVjKi2LrU/default.jpg",
              "width": 120
            },
            "high": {
              "height": 360,
              "url": "https://i.ytimg.com/vi/ctiVjKi2LrU/hqdefault.jpg",
              "width": 480
            },
            "medium": {
              "height": 180,
              "url": "https://i.ytimg.com/vi/ctiVjKi2LrU/mqdefault.jpg",
              "width": 320
            }
          },
          "title": "Live A.M.A. (02/04/2026) - GEO Agent is Coming!"
        }
      },
      {
        "etag": "eHT8Hss3CEtV5vAmHyNuBaTtDMg",
        "id": {
          "kind": "youtube#video",
          "videoId": "bw83Z71GQzo"
        },
        "kind": "youtube#searchResult",
        "snippet": {
          "channelId": "UCZm2kvByDm6st8b_x7Dsf7w",
          "channelTitle": "Climbo - Start Your AI Business",
          "description": "Start Your AI Business: https://climbo.com Free Community: https://skool.climbo.com.",
          "liveBroadcastContent": "none",
          "publishTime": "2026-03-13T11:46:15Z",
          "publishedAt": "2026-03-13T11:46:15Z",
          "thumbnails": {
            "default": {
              "height": 90,
              "url": "https://i.ytimg.com/vi/bw83Z71GQzo/default.jpg",
              "width": 120
            },
            "high": {
              "height": 360,
              "url": "https://i.ytimg.com/vi/bw83Z71GQzo/hqdefault.jpg",
              "width": 480
            },
            "medium": {
              "height": 180,
              "url": "https://i.ytimg.com/vi/bw83Z71GQzo/mqdefault.jpg",
              "width": 320
            }
          },
          "title": "Live A.M.A. (12/03/2026) - Review Request Reminders \u0026amp; Custom Links!"
        }
      },
      {
        "etag": "8n2aqWG8fcUiMkcQoO_VirrUxFs",
        "id": {
          "kind": "youtube#video",
          "videoId": "yAx4pzDTmsY"
        },
        "kind": "youtube#searchResult",
        "snippet": {
          "channelId": "UCZm2kvByDm6st8b_x7Dsf7w",
          "channelTitle": "Climbo - Start Your AI Business",
          "description": "Start Your AI Business: https://climbo.com Free Community: https://skool.climbo.com.",
          "liveBroadcastContent": "none",
          "publishTime": "2026-03-06T10:26:59Z",
          "publishedAt": "2026-03-06T10:26:59Z",
          "thumbnails": {
            "default": {
              "height": 90,
              "url": "https://i.ytimg.com/vi/yAx4pzDTmsY/default.jpg",
              "width": 120
            },
            "high": {
              "height": 360,
              "url": "https://i.ytimg.com/vi/yAx4pzDTmsY/hqdefault.jpg",
              "width": 480
            },
            "medium": {
              "height": 180,
              "url": "https://i.ytimg.com/vi/yAx4pzDTmsY/mqdefault.jpg",
              "width": 320
            }
          },
          "title": "Live A.M.A. (05/03/2026) - Turn On/Off Review Link Features on Custom Plans!"
        }
      },
      {
        "etag": "uN6vljOi4FalB6Ac8VvJZHRkVhc",
        "id": {
          "kind": "youtube#video",
          "videoId": "oPElvf0vT6Y"
        },
        "kind": "youtube#searchResult",
        "snippet": {
          "channelId": "UCZm2kvByDm6st8b_x7Dsf7w",
          "channelTitle": "Climbo - Start Your AI Business",
          "description": "Start Your AI Business: https://climbo.com Free Community: https://skool.climbo.com.",
          "liveBroadcastContent": "none",
          "publishTime": "2026-06-05T08:45:44Z",
          "publishedAt": "2026-06-05T08:45:44Z",
          "thumbnails": {
            "default": {
              "height": 90,
              "url": "https://i.ytimg.com/vi/oPElvf0vT6Y/default.jpg",
              "width": 120
            },
            "high": {
              "height": 360,
              "url": "https://i.ytimg.com/vi/oPElvf0vT6Y/hqdefault.jpg",
              "width": 480
            },
            "medium": {
              "height": 180,
              "url": "https://i.ytimg.com/vi/oPElvf0vT6Y/mqdefault.jpg",
              "width": 320
            }
          },
          "title": "Live A.M.A. (04/06/2026) - AI Token Allocation for Clients"
        }
      },
      {
        "etag": "VamSfgvkTljQgl870semBWjM1Yk",
        "id": {
          "kind": "youtube#video",
          "videoId": "HZ-9avetOnE"
        },
        "kind": "youtube#searchResult",
        "snippet": {
          "channelId": "UCZm2kvByDm6st8b_x7Dsf7w",
          "channelTitle": "Climbo - Start Your AI Business",
          "description": "Start and Grow your AI Local Agency: https://climbo.com.",
          "liveBroadcastContent": "none",
          "publishTime": "2026-06-26T08:41:56Z",
          "publishedAt": "2026-06-26T08:41:56Z",
          "thumbnails": {
            "default": {
              "height": 90,
              "url": "https://i.ytimg.com/vi/HZ-9avetOnE/default.jpg",
              "width": 120
            },
            "high": {
              "height": 360,
              "url": "https://i.ytimg.com/vi/HZ-9avetOnE/hqdefault.jpg",
              "width": 480
            },
            "medium": {
              "height": 180,
              "url": "https://i.ytimg.com/vi/HZ-9avetOnE/mqdefault.jpg",
              "width": 320
            }
          },
          "title": "Live A.M.A. (25/06/2026) - SMTP For Review Requests, Coupon Codes, Email History, \u0026amp; More!"
        }
      },
      {
        "etag": "mPKsClP7wq0oM8kyb4AYk3LT_gA",
        "id": {
          "kind": "youtube#video",
          "videoId": "60nbKPfQ-eA"
        },
        "kind": "youtube#searchResult",
        "snippet": {
          "channelId": "UCZm2kvByDm6st8b_x7Dsf7w",
          "channelTitle": "Climbo - Start Your AI Business",
          "description": "Start and Grow your AI Local Agency: https://climbo.com.",
          "liveBroadcastContent": "none",
          "publishTime": "2026-06-19T08:25:56Z",
          "publishedAt": "2026-06-19T08:25:56Z",
          "thumbnails": {
            "default": {
              "height": 90,
              "url": "https://i.ytimg.com/vi/60nbKPfQ-eA/default.jpg",
              "width": 120
            },
            "high": {
              "height": 360,
              "url": "https://i.ytimg.com/vi/60nbKPfQ-eA/hqdefault.jpg",
              "width": 480
            },
            "medium": {
              "height": 180,
              "url": "https://i.ytimg.com/vi/60nbKPfQ-eA/mqdefault.jpg",
              "width": 320
            }
          },
          "title": "Live A.M.A. (04/06/2026) - Launch Your Own Affiliate Program!"
        }
      },
      {
        "etag": "TFGKDY7Ft8nCFgKIQFPWjqJHTuQ",
        "id": {
          "kind": "youtube#video",
          "videoId": "qo0YRSxQgIU"
        },
        "kind": "youtube#searchResult",
        "snippet": {
          "channelId": "UCZm2kvByDm6st8b_x7Dsf7w",
          "channelTitle": "Climbo - Start Your AI Business",
          "description": "",
          "liveBroadcastContent": "none",
          "publishTime": "2026-06-17T09:27:15Z",
          "publishedAt": "2026-06-17T09:27:15Z",
          "thumbnails": {
            "default": {
              "height": 90,
              "url": "https://i.ytimg.com/vi/qo0YRSxQgIU/default.jpg",
              "width": 120
            },
            "high": {
              "height": 360,
              "url": "https://i.ytimg.com/vi/qo0YRSxQgIU/hqdefault.jpg",
              "width": 480
            },
            "medium": {
              "height": 180,
              "url": "https://i.ytimg.com/vi/qo0YRSxQgIU/mqdefault.jpg",
              "width": 320
            }
          },
          "title": "Balance Explained: Messaging \u0026amp; AI Costs"
        }
      },
      {
        "etag": "teMGFWy5BoEyWf4vogFtYDUJmmo",
        "id": {
          "kind": "youtube#video",
          "videoId": "heg4L7e0QNs"
        },
        "kind": "youtube#searchResult",
        "snippet": {
          "channelId": "UCZm2kvByDm6st8b_x7Dsf7w",
          "channelTitle": "Climbo - Start Your AI Business",
          "description": "Start and Grow your AI Local Agency: https://climbo.com.",
          "liveBroadcastContent": "none",
          "publishTime": "2026-07-03T13:47:48Z",
          "publishedAt": "2026-07-03T13:47:48Z",
          "thumbnails": {
            "default": {
              "height": 90,
              "url": "https://i.ytimg.com/vi/heg4L7e0QNs/default.jpg",
              "width": 120
            },
            "high": {
              "height": 360,
              "url": "https://i.ytimg.com/vi/heg4L7e0QNs/hqdefault.jpg",
              "width": 480
            },
            "medium": {
              "height": 180,
              "url": "https://i.ytimg.com/vi/heg4L7e0QNs/mqdefault.jpg",
              "width": 320
            }
          },
          "title": "Live A.M.A. (01/07/2026) - Trial Limits, Google Event/Offer Posts, Stripe Accounting, \u0026amp; More!"
        }
      },
      {
        "etag": "TXgfeKQxfOfeFvgzudczvLAQVhw",
        "id": {
          "kind": "youtube#video",
          "videoId": "e7WP2_j-Gmk"
        },
        "kind": "youtube#searchResult",
        "snippet": {
          "channelId": "UCZm2kvByDm6st8b_x7Dsf7w",
          "channelTitle": "Climbo - Start Your AI Business",
          "description": "New in Climbo: your AI, fully branded. Agencies can now customize the entire AI experience for their clients. Give your AI its own ...",
          "liveBroadcastContent": "none",
          "publishTime": "2026-05-21T15:29:30Z",
          "publishedAt": "2026-05-21T15:29:30Z",
          "thumbnails": {
            "default": {
              "height": 90,
              "url": "https://i.ytimg.com/vi/e7WP2_j-Gmk/default.jpg",
              "width": 120
            },
            "high": {
              "height": 360,
              "url": "https://i.ytimg.com/vi/e7WP2_j-Gmk/hqdefault.jpg",
              "width": 480
            },
            "medium": {
              "height": 180,
              "url": "https://i.ytimg.com/vi/e7WP2_j-Gmk/mqdefault.jpg",
              "width": 320
            }
          },
          "title": "New in Climbo: your AI, fully branded."
        }
      },
      {
        "etag": "oYuUTwMj8fzUVcAR13Hb36YOT4I",
        "id": {
          "kind": "youtube#video",
          "videoId": "12NwL4G8vIE"
        },
        "kind": "youtube#searchResult",
        "snippet": {
          "channelId": "UCZm2kvByDm6st8b_x7Dsf7w",
          "channelTitle": "Climbo - Start Your AI Business",
          "description": "Start and Grow your AI Local Agency: https://climbo.com.",
          "liveBroadcastContent": "none",
          "publishTime": "2026-07-10T20:18:06Z",
          "publishedAt": "2026-07-10T20:18:06Z",
          "thumbnails": {
            "default": {
              "height": 90,
              "url": "https://i.ytimg.com/vi/12NwL4G8vIE/default.jpg",
              "width": 120
            },
            "high": {
              "height": 360,
              "url": "https://i.ytimg.com/vi/12NwL4G8vIE/hqdefault.jpg",
              "width": 480
            },
            "medium": {
              "height": 180,
              "url": "https://i.ytimg.com/vi/12NwL4G8vIE/mqdefault.jpg",
              "width": 320
            }
          },
          "title": "Live A.M.A. (09/07/2026) - Home Charts Are Live!"
        }
      }
    ],
    "kind": "youtube#searchListResponse",
    "pageInfo": {
      "resultsPerPage": 30,
      "totalResults": 30
    },
    "regionCode": "IT"
  }
}
